{"nourishment": 0, "willing": 1, "spite": 2, "normally": 3, "cautious": 4, "lest": 5, "Strada": 6, "John": 7, "recent": 8, "Shop": 9, "Mediterranean": 10, "bend": 11, "competitors": 12, "cheapest": 13, "called": 14, "Cotto": 15, "Fast": 16, "Green": 17, "legal": 18, "Indian": 19, "gathering": 20, "fan": 21, "Cam": 22, "Of": 23, "attracting": 24, "vary": 25, "steak": 26, "Beefeater": 27, "slice": 28, "offerings": 29, "IT": 30, "Asian": 31, "recognized": 32, "epitome": 33, "consumer": 34, "Aromi": 35, "reason": 36, "range": 37, "closely": 38, "Establishment": 39, "bakery": 40, "eve": 41, "50": 42, "kids": 43, "part": 44, "comes": 45, "tastings": 46, "Serves": 47, "lowest": 48, "stat": 49, "26": 50, "pub": 51, "Here": 52, "supplies": 53, "sitting": 54, "Competitively": 55, "present": 56, "launching": 57, "Falling": 58, "presents": 59, "riverside": 60, "unable": 61, "if": 62, "Cheese": 63, "Euros": 64, "luxuriant": 65, "munch": 66, "roughly": 67, "freshly": 68, "wrong": 69, "believe": 70, "historical": 71, "dearest": 72, "delivery": 73, "obscene": 74, "30Euro": 75, "heads": 76, "switched": 77, "--": 78, "Great": 79, "elite": 80, "three": 81, "down": 82, "customer": 83, "clients": 84, "contains": 85, "ordinary": 86, "refine": 87, "optional": 88, "Mediocre": 89, "assorted": 90, "NOT": 91, "Quid": 92, "commerce": 93, "ricing": 94, "could": 95, "equally": 96, "Finally": 97, "nights": 98, "spot": 99, "I": 100, "sorts": 101, "went": 102, "Close": 103, "orders": 104, "Style": 105, "Prices": 106, "seems": 107, "respectable": 108, "$": 109, "wasn": 110, "baby": 111, "us": 112, "sushi": 113, "21": 114, "choose": 115, "friending": 116, "dish": 117, "pastries": 118, "ten": 119, "classy": 120, "chaps": 121, "Burgers": 122, "partake": 123, "00": 124, "winning": 125, "out": 126, "coloring": 127, "friendliness": 128, "plates": 129, "sale": 130, "done": 131, "conveniently": 132, "kind": 133, "Typical": 134, "mom": 135, "save": 136, "favourably": 137, "core": 138, "outlet": 139, "Weather": 140, "Riversides": 141, "deal": 142, "considerable": 143, "OK": 144, "know": 145, "offer": 146, "day": 147, "Restaurant": 148, "takeout": 149, "Fruits": 150, "Burger": 151, "steep": 152, "Sat": 153, "ratting": 154, "gym": 155, "sporting": 156, "list": 157, "splendid": 158, "didn": 159, "pick": 160, "beaten": 161, "Will": 162, "combination": 163, "caked": 164, "garners": 165, "rice": 166, "mixed": 167, "cold": 168, "winery": 169, "creating": 170, "Pricey": 171, "hight": 172, ".": 173, "budge": 174, "happy": 175, "flare": 176, "u": 177, "merge": 178, "directions": 179, "diet": 180, "scintillating": 181, "advertise": 182, "east": 183, "table": 184, "perfectly": 185, "honorable": 186, "spent": 187, "Quite": 188, "Environment": 189, "snugly": 190, "luck": 191, "palace": 192, "Dulwich": 193, "advice": 194, "Eat": 195, "from": 196, "healthy": 197, "Downtown": 198, "hole": 199, "People": 200, "open": 201, "thinking": 202, "wines": 203, "All": 204, "rude": 205, "checked": 206, "limits": 207, "might": 208, "lovely": 209, "scenic": 210, "Curry": 211, "breathtaking": 212, "different": 213, "ate": 214, "servings": 215, "setting": 216, "previous": 217, "closer": 218, "Greek": 219, "hither": 220, "combo": 221, "selling": 222, "results": 223, "back": 224, "takes": 225, "Keep": 226, "Breakfasts": 227, "familial": 228, "detracts": 229, "any": 230, "Improving": 231, "joint": 232, "cousin": 233, "later": 234, "Spirits": 235, "road": 236, "Kid": 237, "hello": 238, "decent": 239, "reflection": 240, "cities": 241, "information": 242, "Irresistible": 243, "prime": 244, "East": 245, "Also": 246, "beer": 247, "fairly": 248, "true": 249, "billiard": 250, "ranting": 251, "reduced": 252, "fallen": 253, "Road": 254, "serving": 255, "gaining": 256, "get": 257, "only": 258, "steeply": 259, "specializes": 260, "anti": 261, "stopping": 262, "brings": 263, "convenience": 264, "surroundings": 265, "beautiful": 266, "invited": 267, "locating": 268, "30lb": 269, "lacking": 270, "Described": 271, "130": 272, "should": 273, "exceptional": 274, "which": 275, "beat": 276, "int": 277, "childless": 278, "chains": 279, "in": 280, "exclusive": 281, "Moderated": 282, "items": 283, "existing": 284, "getting": 285, "bite": 286, "Famous": 287, "Mavericks": 288, "Kings": 289, "Hot": 290, "provider": 291, "<start>": 292, "few": 293, "that": 294, "based": 295, "Doesn": 296, "commute": 297, "[\u00a3": 298, "We": 299, "Regularly": 300, "minded": 301, "Expensive": 302, "riverbank": 303, "penny": 304, "turn": 305, "-\u00a3": 306, "light": 307, "Higher": 308, "actively": 309, "Splurge": 310, "France": 311, "mostly": 312, "crowd": 313, "Theme": 314, "continental": 315, "...": 316, "urban": 317, "frequently": 318, "nor": 319, "employees": 320, "abysmal": 321, "Reviewers": 322, "Her": 323, "Fitzbillies": 324, "reviewed": 325, "building": 326, "how": 327, "path": 328, "friendliest": 329, "answer": 330, "games": 331, "sea": 332, "Brazilian": 333, "interesting": 334, "0": 335, "mature": 336, "product": 337, "receive": 338, "hors": 339, "English": 340, "beluga": 341, "population": 342, "potato": 343, "Sicilian": 344, "his": 345, "ranked": 346, "Express": 347, "last": 348, "buds": 349, "Eagle": 350, "hotel": 351, "connected": 352, "amid": 353, "farmers": 354, "vibe": 355, "always": 356, "general": 357, "founded": 358, "scummy": 359, "mimic": 360, "surely": 361, "limited": 362, "goddess": 363, "expansive": 364, "fictional": 365, "leave": 366, "rough": 367, "noodle": 368, "guests": 369, ".'": 370, "wanting": 371, "Majority": 372, "specials": 373, "King": 374, "Fyne": 375, "Averagely": 376, "private": 377, "enjoys": 378, "20L": 379, "Licensed": 380, "intimate": 381, "Caf\u00e9inated": 382, "Most": 383, "than": 384, "upward": 385, "favor": 386, "questionable": 387, "Dogs": 388, "Hill": 389, "scored": 390, "lays": 391, "Coming": 392, "Mia": 393, "unbeatable": 394, "Handicapped": 395, "slap": 396, "customers": 397, "second": 398, "restaurants": 399, "loves": 400, "iron": 401, "Pricing": 402, "around": 403, "American": 404, "Ever": 405, "organization": 406, "entree": 407, "Th": 408, "outskirts": 409, "ore": 410, "shopping": 411, "great": 412, "rouge": 413, "dine": 414, "opening": 415, "location": 416, "fine": 417, "those": 418, "array": 419, "quiet": 420, "ratings": 421, "curry": 422, "coast": 423, "won": 424, "5out": 425, "selection": 426, "ad": 427, "values": 428, "are": 429, "kinds": 430, "baller": 431, "adequately": 432, "welcomed": 433, "highest": 434, "t": 435, "abounds": 436, "ranks": 437, "form": 438, "eatType": 439, "Both": 440, "newly": 441, "sample": 442, "chart": 443, "proves": 444, "specialties": 445, "stationed": 446, "outs": 447, "],": 448, "Further": 449, "restaurantr": 450, "If": 451, "Fynes": 452, "profile": 453, "Having": 454, "........": 455, "cheaply": 456, "Glisson": 457, "ares": 458, "bearable": 459, "varying": 460, "seafood": 461, "carries": 462, "scoring": 463, "l30": 464, "arrangement": 465, "Midsummer": 466, "World": 467, "options": 468, "worse": 469, "follow": 470, "nicer": 471, "like": 472, "enjoy": 473, "Found": 474, "E25": 475, "levels": 476, "',": 477, "distance": 478, "pug": 479, "whether": 480, "On": 481, "steal": 482, "night": 483, "central": 484, "wealthy": 485, "recommenced": 486, "Locate": 487, "riverfront": 488, "anyone": 489, "disallows": 490, "spending": 491, "guarantee": 492, "Based": 493, "obtained": 494, "..": 495, "providers": 496, "visiting": 497, "chips": 498, "covered": 499, "parings": 500, "accordingly": 501, "Foods": 502, "coupled": 503, "related": 504, "id": 505, "terrific": 506, "itself": 507, "Low": 508, "complain": 509, "lower": 510, "bringing": 511, "item": 512, "highly": 513, "discourage": 514, "fro": 515, "amazingly": 516, "Bring": 517, "cit": 518, "He": 519, "searching": 520, "satisfying": 521, "Ranges": 522, "something": 523, "eating": 524, "suck": 525, "25and": 526, "aims": 527, "expert": 528, "Offering": 529, "entertainment": 530, "mainstream": 531, "started": 532, "Man": 533, "Noodles": 534, "gets": 535, "takeaway": 536, "locals": 537, "Rd": 538, "brilliant": 539, "similar": 540, "blue": 541, "Kids": 542, "Sporting": 543, "everyday": 544, "seven": 545, "lakeside": 546, "Name": 547, "specific": 548, "walk": 549, "warm": 550, "0f": 551, "singles": 552, "blocks": 553, "familiar": 554, "quickly": 555, "desired": 556, "purveyor": 557, "Vegetable": 558, "Curried": 559, "Unsuitable": 560, "odd": 561, "Visit": 562, "park": 563, "end": 564, "lacks": 565, "olives": 566, "finished": 567, "trips": 568, "themed": 569, "Their": 570, "stars": 571, "British": 572, "lends": 573, "economic": 574, "university": 575, "permits": 576, "opened": 577, "affording": 578, "southern": 579, "culinary": 580, "discerning": 581, "on": 582, "ask": 583, "wrestling": 584, "grove": 585, "tell": 586, "pun": 587, "Somewhere": 588, "30and": 589, "prohibited": 590, "Recently": 591, ",,": 592, "Beside": 593, "Along": 594, "client": 595, "ultimate": 596, "European": 597, "loved": 598, "does": 599, "avoid": 600, "partner": 601, "wish": 602, "Yippee": 603, "2": 604, "clentele": 605, "desserts": 606, "guy": 607, "generated": 608, "moderately": 609, "Day": 610, "areas": 611, "Very": 612, "small": 613, "aim": 614, "Chesterton": 615, "cause": 616, "spectacular": 617, "dinning": 618, "seen": 619, "its": 620, "House": 621, "generally": 622, "least": 623, "When": 624, "below": 625, "Bakers": 626, "since": 627, "change": 628, "Fresh": 629, "Portland": 630, "Settled": 631, "Centre": 632, "Besides": 633, "cheeseboards": 634, "support": 635, "Northwest": 636, "Adults": 637, "winner": 638, "Cricketers": 639, "'.": 640, "downtown": 641, "enjoying": 642, "Aromis": 643, "simple": 644, "exist": 645, "typically": 646, "excuse": 647, "striking": 648, "easily": 649, "cost": 650, "peoples": 651, "greasy": 652, "Why": 653, "Offers": 654, "orientated": 655, "wallet": 656, "\u00a3.": 657, "or": 658, "Yard": 659, "buy": 660, "menus": 661, "inexpensive": 662, "Tailoring": 663, "Welcome": 664, "euros": 665, "buck": 666, "Away": 667, "Earning": 668, "highchairs": 669, "scenery": 670, "NEA": 671, "lake": 672, "to": 673, "importantly": 674, "tradition": 675, "edible": 676, "proved": 677, "pricey": 678, "fondue": 679, "Hotel": 680, "landmark": 681, "Tim": 682, "old": 683, "cheat": 684, "up": 685, "formal": 686, "minors": 687, "pried": 688, "sold": 689, "unpopular": 690, "contemporary": 691, "dining": 692, "consumers": 693, "Parking": 694, "plus": 695, "comfort": 696, "Canadian": 697, "Alcoholic": 698, "Diners": 699, "inn": 700, "Rice": 701, "pairing": 702, "Adult": 703, "fans": 704, ".\u00a3": 705, "trying": 706, "main": 707, "specialized": 708, "Five": 709, "according": 710, "i": 711, "my": 712, "layout": 713, "Join": 714, "visitor": 715, "Consumers": 716, "meals": 717, "infamously": 718, "sophisticated": 719, "modest": 720, "boasting": 721, "grommet": 722, "fastfood": 723, "Us": 724, "impeccable": 725, "Customers": 726, "makes": 727, "across": 728, "wall": 729, "he": 730, "meal": 731, "m": 732, "dismal": 733, "maintains": 734, "point": 735, "everybody": 736, "Down": 737, "eater": 738, "market": 739, "Ranged": 740, "doing": 741, "accepts": 742, "toy": 743, "besides": 744, "solstice": 745, "vendor": 746, "base": 747, "shoppe": 748, "Quaint": 749, "established": 750, "Now": 751, "including": 752, "students": 753, "Lowly": 754, "chop": 755, "feature": 756, "miss": 757, "smart": 758, "toast": 759, "entire": 760, "come": 761, "competitively": 762, "access": 763, "ethos": 764, "Expensively": 765, "substandard": 766, "were": 767, "Middle": 768, "outing": 769, "award": 770, "adequate": 771, "center": 772, "?": 773, "sub": 774, "likes": 775, "recommending": 776, "Rest": 777, "be": 778, "par": 779, "bargains": 780, "at": 781, "Convenient": 782, "Open": 783, "f": 784, "delightful": 785, "Stars": 786, "fry": 787, "My": 788, "then": 789, "group": 790, "pump": 791, "show": 792, "acceptable": 793, "ranger": 794, "IF": 795, "straight": 796, "bis": 797, "ve": 798, "accommodating": 799, "precisely": 800, "tat": 801, "Hamburger": 802, "15": 803, "disappoint": 804, "croissants": 805, "online": 806, "rather": 807, "owner": 808, "mothers": 809, "can": 810, "Budget": 811, "spendy": 812, "earning": 813, "underrated": 814, "charging": 815, "beware": 816, "jaunt": 817, "led": 818, "Romantic": 819, "unexplained": 820, "off": 821, "fact": 822, "averaged": 823, "audience": 824, "variety": 825, "Plus": 826, "ice": 827, "Beef": 828, "homemade": 829, "refreshments": 830, "To": 831, "L20": 832, "Pounds": 833, "life": 834, "map": 835, "lots": 836, "surpass": 837, "Non": 838, "wants": 839, "Providing": 840, "Ideal": 841, "proximity": 842, "sticks": 843, "Well": 844, "times": 845, "websites": 846, "cool": 847, "Upscale": 848, "Above": 849, "Another": 850, "quite": 851, "give": 852, "noodles": 853, "calming": 854, "Alimentum": 855, "prestigious": 856, "board": 857, "Only": 858, "permit": 859, "noise": 860, "match": 861, "bigger": 862, "Finding": 863, "become": 864, "Travellers": 865, "Italian": 866, "bistro": 867, "costings": 868, "much": 869, "Eagles": 870, "lo": 871, "sadly": 872, "Around": 873, "deemed": 874, "Those": 875, "solo": 876, "30L": 877, "gals": 878, "watering": 879, "whit": 880, "reminded": 881, "economically": 882, "thew": 883, "Italy": 884, "aptly": 885, "assessment": 886, "pasta": 887, "unique": 888, "Ideally": 889, "escargot": 890, "Does": 891, "glass": 892, "lackluster": 893, "facility": 894, "Menu": 895, "grade": 896, "New": 897, "free": 898, "bought": 899, "positive": 900, "crazy": 901, "fall": 902, "lunch": 903, "bells": 904, "neat": 905, "mood": 906, "pint": 907, "Can": 908, "specializing": 909, "constant": 910, "taking": 911, "classier": 912, "products": 913, "couples": 914, "option": 915, "response": 916, "surprise": 917, "arrive": 918, "pretty": 919, "Mid": 920, "they": 921, "sports": 922, "Though": 923, "rivers": 924, "sorry": 925, "shores": 926, "dislocated": 927, "gem": 928, "compared": 929, "5": 930, "good": 931, "Six": 932, "spoon": 933, "hate": 934, "Other": 935, "Home": 936, "hearty": 937, "select": 938, "consider": 939, "whet": 940, "above": 941, "Enjoy": 942, "policy": 943, "miles": 944, "boat": 945, "Be": 946, "dive": 947, "business": 948, "Food": 949, "accompanied": 950, "Atmosphere": 951, "transport": 952, "bathrooms": 953, "Pembroke": 954, "stellar": 955, "Delicious": 956, "City": 957, "costing": 958, "door": 959, "addition": 960, "Caf\u00e9": 961, "From": 962, "wells": 963, "right": 964, "personal": 965, "budgets": 966, "surprisingly": 967, "Freshly": 968, "grub": 969, "softens": 970, "Relatively": 971, "breakfasts": 972, "experiencing": 973, "want": 974, "loving": 975, "welcoming": 976, "happiness": 977, "families": 978, "Hugh": 979, "moved": 980, "rood": 981, "cheep": 982, "deals": 983, "d": 984, "hold": 985, "space": 986, "becoming": 987, "rang": 988, "purchased": 989, "exclusively": 990, "fewer": 991, "staff": 992, "Happy": 993, "banks": 994, "especially": 995, "feedback": 996, "other": 997, "Overall": 998, "worthed": 999, "hot": 1000, "Buns": 1001, "Friend": 1002, "locates": 1003, "sized": 1004, "modern": 1005, "benefit": 1006, "outstanding": 1007, "whose": 1008, "Grill": 1009, "current": 1010, "attractive": 1011, "3": 1012, "cute": 1013, "thirty": 1014, "per": 1015, "9": 1016, "Baker": 1017, "would": 1018, "fix": 1019, "Local": 1020, "recommended": 1021, "sears": 1022, "Zizzi": 1023, "now": 1024, "Rough": 1025, ".,": 1026, "quick": 1027, "warning": 1028, "presently": 1029, "shoo": 1030, "price": 1031, "Clare": 1032, "PS": 1033, "Inns": 1034, "far": 1035, "centric": 1036, "downside": 1037, "Sensibly": 1038, "books": 1039, "use": 1040, "Rating": 1041, "stop": 1042, "zesty": 1043, "must": 1044, "cant": 1045, "hamburgers": 1046, "notch": 1047, "sit": 1048, "recommend": 1049, "various": 1050, "Crowne": 1051, "suited": 1052, "swanky": 1053, "Go": 1054, "Coffee": 1055, "thumbs": 1056, "artisan": 1057, "standards": 1058, "king": 1059, "mildly": 1060, "prove": 1061, "allow": 1062, "intended": 1063, "styled": 1064, "inspired": 1065, "1": 1066, "opinions": 1067, "alternative": 1068, "date": 1069, "useful": 1070, "minimum": 1071, "bathroom": 1072, "taste": 1073, "f30": 1074, "really": 1075, "Its": 1076, "impress": 1077, "peace": 1078, "neighborhood": 1079, "lowly": 1080, "beverages": 1081, "[": 1082, "30GBP": 1083, "Families": 1084, "look": 1085, "food": 1086, "destination": 1087, "ha": 1088, "starred": 1089, "professionally": 1090, "nevertheless": 1091, "quaint": 1092, "Overpriced": 1093, "Slightly": 1094, "cook": 1095, "oriental": 1096, "lot": 1097, "Park": 1098, "equal": 1099, "Which": 1100, "trip": 1101, "Ratings": 1102, "provided": 1103, "relaxed": 1104, "warn": 1105, "wakey": 1106, "quadrant": 1107, "decide": 1108, "poor": 1109, "dollar": 1110, "maximum": 1111, "Moderately": 1112, "OT": 1113, "play": 1114, "northeast": 1115, "atrocious": 1116, "sis": 1117, "daily": 1118, "toys": 1119, "skirts": 1120, "achieving": 1121, "directly": 1122, "fare": 1123, "checkbooks": 1124, "Key": 1125, "located": 1126, "Zizzis": 1127, "India": 1128, "grills": 1129, "Below": 1130, "classed": 1131, "focused": 1132, "Eating": 1133, "falsehood": 1134, "Cheshire": 1135, "Located": 1136, "star": 1137, "stunning": 1138, "soda": 1139, "Rang": 1140, "pounds": 1141, "allows": 1142, "despite": 1143, "unexpected": 1144, "noted": 1145, "Sorry": 1146, "affordable": 1147, "search": 1148, "Set": 1149, "entertain": 1150, "solid": 1151, "oregano": 1152, "comensales": 1153, "Available": 1154, "South": 1155, "Make": 1156, "es": 1157, "mistaken": 1158, "key": 1159, "exceeds": 1160, "witch": 1161, "Costs": 1162, "varieties": 1163, "Hello": 1164, "gained": 1165, "sat": 1166, "disappointed": 1167, "costed": 1168, "Always": 1169, "superior": 1170, "Junior": 1171, "overlooking": 1172, "dubbed": 1173, "find": 1174, "custom": 1175, "rest": 1176, "ambiance": 1177, "improve": 1178, "nice": 1179, "oeuvre": 1180, "This": 1181, "bread": 1182, "Given": 1183, "reaching": 1184, "oeuvres": 1185, "Cocum": 1186, "as": 1187, "sort": 1188, "Some": 1189, "greatly": 1190, "amenities": 1191, "milkshakes": 1192, "famous": 1193, "Moderate": 1194, "soups": 1195, "lives": 1196, "A": 1197, "compatibility": 1198, "dedicated": 1199, "reputation": 1200, "heart": 1201, "expect": 1202, "simply": 1203, "placed": 1204, "anon": 1205, "put": 1206, "groundbreaking": 1207, "build": 1208, "Brazil": 1209, "varied": 1210, "averaging": 1211, "gorgeous": 1212, "Vegetarian": 1213, "selves": 1214, "waterman": 1215, "Anyone": 1216, "brave": 1217, "20": 1218, "Fun": 1219, "tight": 1220, "childhood": 1221, "join": 1222, "unrecommended": 1223, "possible": 1224, "servicing": 1225, "contend": 1226, "Beluga": 1227, "beans": 1228, "Inexpensive": 1229, "head": 1230, "full": 1231, "coffeehouse": 1232, "median": 1233, "surrounding": 1234, "alike": 1235, "several": 1236, "regularly": 1237, "baked": 1238, ",'": 1239, "edge": 1240, "individuals": 1241, "bound": 1242, "fits": 1243, "3of5": 1244, "pit": 1245, "scene": 1246, "Delivers": 1247, "Charging": 1248, "perfect": 1249, "GBP": 1250, "Beware": 1251, "see": 1252, "resulting": 1253, "achieved": 1254, "States": 1255, "Oriented": 1256, "ok": 1257, "Nestled": 1258, "large": 1259, "Bibimbap": 1260, "unbelievable": 1261, "quality": 1262, "DE": 1263, "falling": 1264, "organizations": 1265, "diners": 1266, "peaceful": 1267, "Highest": 1268, "relocating": 1269, "starts": 1270, "slightly": 1271, "older": 1272, "Maybe": 1273, "riddle": 1274, "provides": 1275, "premises": 1276, "furniture": 1277, "wine": 1278, "competes": 1279, "Reasonably": 1280, "nearest": 1281, "coveted": 1282, "passing": 1283, "rive": 1284, "Chinese": 1285, "evening": 1286, "Bargain": 1287, "check": 1288, "appear": 1289, "excellent": 1290, "example": 1291, "Classic": 1292, "convenient": 1293, "standard": 1294, "25L": 1295, "northwest": 1296, "says": 1297, "experiences": 1298, "grocery": 1299, "eatery": 1300, "ridiculously": 1301, "shut": 1302, "also": 1303, "merits": 1304, "Perhaps": 1305, "rand": 1306, "charge": 1307, "handy": 1308, "While": 1309, "Love": 1310, "pairings": 1311, "site": 1312, "ran": 1313, "nightlife": 1314, "Nearby": 1315, "dear": 1316, "Medium": 1317, "graded": 1318, "pizza": 1319, "Tired": 1320, "our": 1321, "pound": 1322, "Look": 1323, "extremely": 1324, "Feed": 1325, "them": 1326, "qualification": 1327, "restroom": 1328, "focus": 1329, "happen": 1330, "overall": 1331, "simultaneously": 1332, "rating3": 1333, "Not": 1334, "rear": 1335, "a": 1336, "next": 1337, "tends": 1338, "fares": 1339, "long": 1340, "Poor": 1341, "decadent": 1342, "cheeses": 1343, "Olive": 1344, "treat": 1345, "Picturesque": 1346, "nests": 1347, "5of5located": 1348, "therefore": 1349, "yet": 1350, "rave": 1351, "of5": 1352, "Plough": 1353, "purchase": 1354, "thirsty": 1355, "famed": 1356, "bakes": 1357, "cite": 1358, "styling": 1359, "somewhere": 1360, "living": 1361, "Whole": 1362, "is": 1363, "prices": 1364, "After": 1365, "Chelsea": 1366, "Less": 1367, "going": 1368, "certainly": 1369, "merely": 1370, "misguided": 1371, "roast": 1372, "company": 1373, "had": 1374, "tasting": 1375, "L": 1376, "because": 1377, "campus": 1378, "discount": 1379, "meant": 1380, "complete": 1381, "Full": 1382, "Ranked": 1383, "Eatery": 1384, "stone": 1385, "another": 1386, "Twenty": 1387, "eats": 1388, "way": 1389, "landed": 1390, "awed": 1391, "although": 1392, "activities": 1393, "May": 1394, "sits": 1395, "antipasto": 1396, "Our": 1397, "leads": 1398, "pointer": 1399, "meets": 1400, "categories": 1401, "seeking": 1402, "minutes": 1403, "sterling": 1404, "emerging": 1405, "please": 1406, "set": 1407, "Friendly": 1408, "shops": 1409, "break": 1410, "Boat": 1411, "Conveniently": 1412, "shows": 1413, "named": 1414, "alongside": 1415, "Spaghetti": 1416, ";": 1417, "Giraffe": 1418, "Centrally": 1419, "kitchen": 1420, "succulent": 1421, "may": 1422, "ones": 1423, "additionally": 1424, "nearby": 1425, "services": 1426, "over": 1427, "behind": 1428, "prince": 1429, "delivers": 1430, "include": 1431, "sacrifice": 1432, "encounter": 1433, "patrons": 1434, "position": 1435, "dishes": 1436, "who": 1437, "wit": 1438, "geared": 1439, "feel": 1440, "Star": 1441, "ahead": 1442, "excellence": 1443, "Euro": 1444, "gave": 1445, "appeal": 1446, "8": 1447, "traditionally": 1448, "one": 1449, "waterside": 1450, "holding": 1451, "requires": 1452, "Spice": 1453, "describe": 1454, "actually": 1455, "clowns": 1456, "consistent": 1457, "cracker": 1458, "5customer": 1459, "help": 1460, "drain": 1461, "perhaps": 1462, "rated": 1463, "\u00a3": 1464, "things": 1465, "Please": 1466, "reports": 1467, "need": 1468, "served": 1469, "Across": 1470, "every": 1471, "outside": 1472, "Rouge": 1473, "burgers": 1474, "further": 1475, "wonder": 1476, "pastas": 1477, "Drop": 1478, "And": 1479, "Forbid": 1480, "tapa": 1481, "Cheaply": 1482, "tier": 1483, "leaves": 1484, "kiddos": 1485, "Nice": 1486, "revived": 1487, "frugally": 1488, "incredible": 1489, "fruit": 1490, "finery": 1491, "Thai": 1492, "looks": 1493, "syndrome": 1494, "truly": 1495, "Tuscan": 1496, "en": 1497, "groups": 1498, "with": 1499, "their": 1500, "mere": 1501, "worker": 1502, "amicable": 1503, "features": 1504, "ranged": 1505, "praised": 1506, "Need": 1507, "liked": 1508, "More": 1509, "thats": 1510, "Alongside": 1511, "super": 1512, "sizes": 1513, "samples": 1514, "listed": 1515, "e": 1516, "competing": 1517, "Golden": 1518, "getaway": 1519, "Isn": 1520, "grapes": 1521, "community": 1522, "note": 1523, ":\u00a3": 1524, "visitors": 1525, "lively": 1526, "hungry": 1527, "soup": 1528, "decided": 1529, "Within": 1530, "Average": 1531, "y": 1532, "luxury": 1533, "shown": 1534, "stomach": 1535, "mean": 1536, "high": 1537, "Good": 1538, "cravings": 1539, "20s": 1540, "pleasant": 1541, "exceed": 1542, "cheap": 1543, "short": 1544, "finding": 1545, "s": 1546, "inviting": 1547, "boast": 1548, "Scoring": 1549, "tied": 1550, "drop": 1551, "suggest": 1552, "appetizers": 1553, "types": 1554, "adult": 1555, "Area": 1556, "Whenever": 1557, "Ranch": 1558, "restrooms": 1559, "slight": 1560, "bakeries": 1561, "exactly": 1562, "That": 1563, "amazing": 1564, "low": 1565, ",\u00a3": 1566, "elegant": 1567, "refreshment": 1568, "citing": 1569, "area": 1570, "very": 1571, "safe": 1572, "Fastfood": 1573, "wide": 1574, "without": 1575, "rests": 1576, "do": 1577, "Mill": 1578, "little": 1579, "finest": 1580, "coming": 1581, "reserving": 1582, "calm": 1583, "casual": 1584, "ethnic": 1585, "favourite": 1586, "sausage": 1587, "palates": 1588, "speaking": 1589, "real": 1590, "holds": 1591, "purely": 1592, "delegate": 1593, "establishments": 1594, "rare": 1595, "Punters": 1596, "lovers": 1597, "cocktails": 1598, "think": 1599, "establishment": 1600, "nestled": 1601, "law": 1602, "exceeding": 1603, "Unfortunately": 1604, "issues": 1605, "sustenance": 1606, "Crown": 1607, "too": 1608, "paying": 1609, "reported": 1610, "middle": 1611, "burger": 1612, "regular": 1613, "hamburger": 1614, "bargain": 1615, "Winery": 1616, "Sushi": 1617, "infamous": 1618, "gut": 1619, "found": 1620, "Grove": 1621, "shout": 1622, "reasons": 1623, "Sitting": 1624, "feet": 1625, "go": 1626, "hefty": 1627, "love": 1628, "excels": 1629, "popularity": 1630, "added": 1631, "carer": 1632, "catering": 1633, "Featuring": 1634, "city": 1635, "ranking": 1636, "leaving": 1637, "close": 1638, "man": 1639, "averages": 1640, "don": 1641, "south": 1642, "33": 1643, "hosts": 1644, "Get": 1645, "five": 1646, "There": 1647, "made": 1648, "aimed": 1649, "overly": 1650, "picturesque": 1651, "delicacies": 1652, "ingredients": 1653, "requirements": 1654, "Three": 1655, "Luckily": 1656, "Far": 1657, "qualified": 1658, "vast": 1659, "Peas": 1660, "North": 1661, "Variety": 1662, "Since": 1663, "comfortable": 1664, "reside": 1665, "regret": 1666, "rich": 1667, "blow": 1668, "surprising": 1669, "Named": 1670, "standing": 1671, "outer": 1672, "Location": 1673, "mediocre": 1674, "major": 1675, "marked": 1676, "ages": 1677, "Even": 1678, "25lb": 1679, "mix": 1680, "Head": 1681, "Traditional": 1682, "sodas": 1683, "begin": 1684, ":": 1685, "Grand": 1686, "street": 1687, "Mama": 1688, "romantic": 1689, "Scores": 1690, "all": 1691, "carryout": 1692, "Oriental": 1693, "pop": 1694, "non": 1695, "Noodle": 1696, "zone": 1697, "accommodates": 1698, "AVERAGE": 1699, "hope": 1700, "instead": 1701, "predominantly": 1702, "1out5": 1703, "They": 1704, "diner": 1705, "An": 1706, "chill": 1707, "mare": 1708, "bottle": 1709, "bacon": 1710, "bustling": 1711, "Outside": 1712, "sausages": 1713, "away": 1714, "store": 1715, "average": 1716, "section": 1717, "indulge": 1718, "Sited": 1719, "Amongst": 1720, "Browns": 1721, "Perfect": 1722, "Taste": 1723, "fun": 1724, "Europe": 1725, "coffee": 1726, "style": 1727, "exquisite": 1728, "points": 1729, "In": 1730, "flavorful": 1731, "Vaults": 1732, "for": 1733, "hop": 1734, "sited": 1735, "popped": 1736, "Excellent": 1737, "remains": 1738, "Pub": 1739, "operate": 1740, "appropriate": 1741, "reviews": 1742, "weary": 1743, "25": 1744, "cuisine": 1745, "marks": 1746, "strolling": 1747, "after": 1748, "Is": 1749, "helps": 1750, "you": 1751, "no": 1752, "meat": 1753, "slow": 1754, "brew": 1755, "cuz": 1756, "30": 1757, "hat": 1758, "same": 1759, "northwestern": 1760, "either": 1761, "hamgurgers": 1762, "serve": 1763, "Superb": 1764, "sun": 1765, "work": 1766, "Cotton": 1767, "accept": 1768, "prefer": 1769, "enjoyed": 1770, "dis": 1771, "waters": 1772, "Everyone": 1773, "Phoenix": 1774, "costumers": 1775, "specialises": 1776, "guest": 1777, "tourist": 1778, "Stop": 1779, "dollars": 1780, "sure": 1781, "Amazing": 1782, "along": 1783, "delicious": 1784, "moderates": 1785, "best": 1786, "5star": 1787, "approximately": 1788, "fabulous": 1789, "walking": 1790, "comparison": 1791, "feed": 1792, "buyers": 1793, "USA": 1794, "guarantees": 1795, "bad": 1796, "falls": 1797, "indeed": 1798, "n": 1799, "primarily": 1800, "supported": 1801, "remaining": 1802, "share": 1803, "E20": 1804, "Riverside": 1805, "poorly": 1806, "ideal": 1807, "So": 1808, "pricing": 1809, "rank": 1810, "Pound": 1811, "No": 1812, "there": 1813, "spenders": 1814, "Meals": 1815, "oriented": 1816, "Customer": 1817, "given": 1818, "plans": 1819, "closed": 1820, "travel": 1821, "delights": 1822, "underneath": 1823, "running": 1824, "dull": 1825, "Rates": 1826, "unsatisfied": 1827, "mention": 1828, "property": 1829, "Arms": 1830, "usually": 1831, "severs": 1832, "welcomes": 1833, "looking": 1834, "traveling": 1835, "Stay": 1836, "latest": 1837, "awesome": 1838, "awful": 1839, "rival": 1840, "upwards": 1841, "crowds": 1842, "own": 1843, "young": 1844, "soon": 1845, "world": 1846, "celebrating": 1847, "considering": 1848, "parents": 1849, "suppliers": 1850, "\u00a3-": 1851, "extra": 1852, "opposite": 1853, "Among": 1854, "offered": 1855, "spices": 1856, "facilities": 1857, "99": 1858, "richer": 1859, "shrimp": 1860, "earned": 1861, "Affordable": 1862, "enough": 1863, "High": 1864, "approx": 1865, "Adriatic": 1866, "Chines": 1867, "desire": 1868, "permitted": 1869, "linguists": 1870, "Popular": 1871, "Palace": 1872, "!": 1873, "explains": 1874, "between": 1875, "overpriced": 1876, "through": 1877, "advised": 1878, "Pop": 1879, "licensed": 1880, "focuses": 1881, "whiskey": 1882, "escape": 1883, "higher": 1884, "has": 1885, "stay": 1886, "competitive": 1887, "fusion": 1888, "Venue": 1889, "priceRange": 1890, "however": 1891, "h": 1892, "together": 1893, "Dumpling": 1894, "near": 1895, "lbs": 1896, "modestly": 1897, "gastro": 1898, "re": 1899, "loch": 1900, "wrestlers": 1901, "matches": 1902, "forget": 1903, "5The": 1904, "among": 1905, "bites": 1906, "round": 1907, "Outstanding": 1908, "stake": 1909, "overs": 1910, "suffers": 1911, "32": 1912, "due": 1913, "premium": 1914, "score": 1915, "choice": 1916, "averagely": 1917, "superb": 1918, "Wrestlers": 1919, "budget": 1920, "suit": 1921, "openly": 1922, "gleaming": 1923, "relaxing": 1924, "liking": 1925, "means": 1926, "Has": 1927, "Fore": 1928, "lending": 1929, "Situated": 1930, "medium": 1931, "beside": 1932, "continues": 1933, "resides": 1934, "reflect": 1935, "scared": 1936, "Public": 1937, "clientele": 1938, "recommendation": 1939, "prepare": 1940, "fond": 1941, "inexpensively": 1942, "Rainbow": 1943, "wise": 1944, "Serving": 1945, "we": 1946, "tapas": 1947, "thrown": 1948, "babies": 1949, "Japan": 1950, "report": 1951, "tall": 1952, "sensibly": 1953, "where": 1954, "plenty": 1955, "staying": 1956, "rate": 1957, "so": 1958, "special": 1959, "Must": 1960, "been": 1961, "prance": 1962, "parking": 1963, "Kick": 1964, "beautifully": 1965, "pleased": 1966, "costly": 1967, "prepared": 1968, "choices": 1969, "Like": 1970, "reviewers": 1971, "est": 1972, "St": 1973, "almost": 1974, "absolutely": 1975, "Ethnic": 1976, "Yet": 1977, "an": 1978, "proudly": 1979, "and": 1980, "multicultural": 1981, "favourable": 1982, "Bringing": 1983, "most": 1984, "bill": 1985, "obviously": 1986, "suitable": 1987, "authentic": 1988, "scores": 1989, "Normally": 1990, "Theres": 1991, "enjoyable": 1992, "socialize": 1993, "was": 1994, "energy": 1995, "unsuitable": 1996, "respected": 1997, "moder": 1998, "size": 1999, "considered": 2000, "here": 2001, "cozy": 2002, "pocket": 2003, "about": 2004, "fires": 2005, "what": 2006, "say": 2007, "Japanese": 2008, "Place": 2009, "Visiting": 2010, "How": 2011, "implores": 2012, "pup": 2013, "Between": 2014, "Vault": 2015, "strategically": 2016, "Facilities": 2017, "value": 2018, "many": 2019, "alcohol": 2020, "liquor": 2021, "touts": 2022, "performing": 2023, "Mills": 2024, "fishes": 2025, "alternatives": 2026, "Reasonable": 2027, "Best": 2028, "hard": 2029, "delectable": 2030, "enter": 2031, "classic": 2032, "Reviews": 2033, "goodies": 2034, "Spend": 2035, "l": 2036, "Northern": 2037, "Indiana": 2038, "fried": 2039, "scare": 2040, "His": 2041, "care": 2042, "rage": 2043, "starting": 2044, "Last": 2045, "costumer": 2046, "okay": 2047, "decently": 2048, "5of5": 2049, "basic": 2050, "friendly": 2051, "mark": 2052, "playground": 2053, "5Located": 2054, "Called": 2055, "age": 2056, "beast": 2057, "everything": 2058, "rating": 2059, "allowed": 2060, "four": 2061, "maximal": 2062, "22": 2063, "waterfront": 2064, "edibles": 2065, "Boasting": 2066, "cup": 2067, "held": 2068, "golden": 2069, "Opposite": 2070, "Loch": 2071, "vicinity": 2072, "shouldn": 2073, "ambient": 2074, "drink": 2075, "money": 2076, "provide": 2077, "under": 2078, "home": 2079, "valuable": 2080, "drive": 2081, "modernly": 2082, "deliver": 2083, "new": 2084, "Plates": 2085, "big": 2086, "native": 2087, "available": 2088, "grab": 2089, "the": 2090, "Price": 2091, "Age": 2092, "amount": 2093, "25pounds": 2094, "3out": 2095, "view": 2096, "addictive": 2097, "Your": 2098, "needs": 2099, "residents": 2100, "nature": 2101, "stands": 2102, "red": 2103, "End": 2104, "neighbourhood": 2105, "front": 2106, "o": 2107, "review": 2108, "Suitable": 2109, "runs": 2110, "Blow": 2111, "nicely": 2112, "breaking": 2113, "appetite": 2114, "Note": 2115, "trouble": 2116, "generously": 2117, "bear": 2118, "titled": 2119, "Or": 2120, "well": 2121, "mind": 2122, "spirits": 2123, "What": 2124, "mainly": 2125, "Shrimp": 2126, "incorporates": 2127, "relax": 2128, "just": 2129, "views": 2130, "watching": 2131, "aware": 2132, "invite": 2133, "to5": 2134, "Adjacent": 2135, "or5": 2136, "offers": 2137, "Rate": 2138, "attraction": 2139, "tea": 2140, "gas": 2141, "ranch": 2142, "reach": 2143, "E30": 2144, "scale": 2145, "via": 2146, "likely": 2147, "backed": 2148, "larger": 2149, "class": 2150, "pricier": 2151, "boot": 2152, "highways": 2153, "tasty": 2154, "priced": 2155, "expensive": 2156, "opinion": 2157, "club": 2158, "fries": 2159, "E50": 2160, "braking": 2161, "waiting": 2162, "Tree": 2163, "careful": 2164, "bakey": 2165, "unsurpassed": 2166, "take": 2167, "visited": 2168, "chain": 2169, "attracts": 2170, "against": 2171, "Friendliness": 2172, "whine": 2173, "Hortons": 2174, "/": 2175, "treats": 2176, "difficult": 2177, "interested": 2178, "olive": 2179, "4": 2180, "ever": 2181, "tempting": 2182, "opportunity": 2183, "According": 2184, "Ranting": 2185, "heard": 2186, "tend": 2187, "but": 2188, "assortment": 2189, "cheese": 2190, "Being": 2191, "yes": 2192, "lowbrow": 2193, "Waterman": 2194, "Mercie": 2195, "have": 2196, "order": 2197, "warrant": 2198, "coffees": 2199, "manageable": 2200, "discover": 2201, "curious": 2202, "Lets": 2203, "earth": 2204, "perks": 2205, "sells": 2206, "settings": 2207, "environment": 2208, "rolls": 2209, "still": 2210, "vaults": 2211, "worthy": 2212, "gains": 2213, "level": 2214, "20GBP": 2215, "Sells": 2216, "Currently": 2217, "affordably": 2218, "unfriendly": 2219, "attained": 2220, "events": 2221, "Gastropub": 2222, "let": 2223, "prestige": 2224, "locate": 2225, "described": 2226, "ship": 2227, "house": 2228, "start": 2229, "Children": 2230, "alone": 2231, "United": 2232, "Over": 2233, "Check": 2234, "ain": 2235, "side": 2236, "able": 2237, "specialist": 2238, "handicap": 2239, "mouth": 2240, "Ah": 2241, "number": 2242, "mile": 2243, "basis": 2244, "Avalon": 2245, "prizes": 2246, "making": 2247, "ingratiating": 2248, "ride": 2249, "conducive": 2250, "strollers": 2251, "your": 2252, "e20": 2253, "Cambridge": 2254, "directed": 2255, "yo": 2256, "favored": 2257, "Range": 2258, "meet": 2259, "Although": 2260, "situated": 2261, "Clowns": 2262, "not": 2263, "Wendy": 2264, "expectations": 2265, "Often": 2266, "familyFriendly": 2267, "having": 2268, "whee": 2269, "this": 2270, "built": 2271, "doesn": 2272, "both": 2273, "thee": 2274, "moderated": 2275, "role": 2276, "scroll": 2277, "neighbor": 2278, "possesses": 2279, "boost": 2280, "<pad>": 2281, "Dine": 2282, "Inn": 2283, "specifically": 2284, "receives": 2285, "everyone": 2286, "Satisfied": 2287, "cater": 2288, "status": 2289, "first": 2290, "Lasagna": 2291, "featured": 2292, "people": 2293, "fancy": 2294, "Costumer": 2295, "20lb": 2296, "said": 2297, "Fitzbilies": 2298, "wares": 2299, "Meal": 2300, "problem": 2301, "River": 2302, "boats": 2303, "excess": 2304, "children": 2305, "platters": 2306, "playgrounds": 2307, "satisfied": 2308, "remarkable": 2309, "venue": 2310, "Hall": 2311, "remember": 2312, "upscale": 2313, "user": 2314, ".......": 2315, "gate": 2316, "tag": 2317, "McDonalds": 2318, "seafare": 2319, "anywhere": 2320, "while": 2321, "time": 2322, "neighbour": 2323, "two": 2324, "steps": 2325, "caters": 2326, "caused": 2327, "Sicilia": 2328, "throw": 2329, "unfavourable": 2330, "tree": 2331, "of": 2332, "Take": 2333, "Highly": 2334, "phoenix": 2335, "spectrum": 2336, "selections": 2337, "hires": 2338, "charming": 2339, "block": 2340, "shabby": 2341, "scrum": 2342, "locally": 2343, "towards": 2344, "Receiving": 2345, "tourists": 2346, "often": 2347, "service": 2348, "servers": 2349, "soft": 2350, "Ravings": 2351, "favorite": 2352, "shot": 2353, "Chopsticks": 2354, "pass": 2355, "Child": 2356, "god": 2357, "prepares": 2358, "ranging": 2359, "French": 2360, "Type": 2361, "produces": 2362, "You": 2363, "moment": 2364, "welcome": 2365, "dinner": 2366, "costs": 2367, "relative": 2368, "relatively": 2369, "western": 2370, "acclaimed": 2371, "worth": 2372, "closest": 2373, "preferred": 2374, "chopping": 2375, "west": 2376, "moire": 2377, "days": 2378, "bank": 2379, "washed": 2380, "Arcade": 2381, "Cuisine": 2382, "usual": 2383, "Known": 2384, "3o": 2385, "deserves": 2386, "Trinity": 2387, "impressive": 2388, "cones": 2389, "picnic": 2390, "joints": 2391, "accommodated": 2392, "tab": 2393, "snacks": 2394, "ff": 2395, "Specialized": 2396, "tale": 2397, "But": 2398, "breads": 2399, "Caf\u00e9teria": 2400, "likable": 2401, "Bar": 2402, "Seen": 2403, "giving": 2404, "somewhat": 2405, "Additionally": 2406, "foot": 2407, "23": 2408, "6": 2409, "<end>": 2410, "adventuress": 2411, "reserve": 2412, "breakfast": 2413, "keep": 2414, "activity": 2415, "Typically": 2416, "upper": 2417, "judging": 2418, "ring": 2419, "purpose": 2420, "hi": 2421, "cooks": 2422, "atmosphere": 2423, "lobster": 2424, "single": 2425, "Wines": 2426, "drinks": 2427, "Luton": 2428, "twenty": 2429, "reasonably": 2430, "th": 2431, "viewed": 2432, "g": 2433, "bird": 2434, "drinking": 2435, "consistently": 2436, "region": 2437, "Trumpington": 2438, "fortune": 2439, "Dishes": 2440, "some": 2441, "Find": 2442, "houses": 2443, "already": 2444, "sensible": 2445, "Lion": 2446, "Considered": 2447, "Orders": 2448, "kid": 2449, "specialising": 2450, "ans": 2451, "venues": 2452, "even": 2453, "six": 2454, "eagle": 2455, "historic": 2456, "Beer": 2457, "particularly": 2458, "name": 2459, "lace": 2460, "tad": 2461, "glowing": 2462, "Cheeses": 2463, "19": 2464, "hour": 2465, "Wine": 2466, "attitude": 2467, "approved": 2468, "Due": 2469, "emerged": 2470, "nowhere": 2471, "grill": 2472, "fish": 2473, "category": 2474, "Loved": 2475, "definitely": 2476, "quinine": 2477, "northern": 2478, "wont": 2479, "Yippe": 2480, "Carryout": 2481, "increasingly": 2482, "water": 2483, "However": 2484, "pay": 2485, "rant": 2486, "restaurant": 2487, "chines": 2488, "cream": 2489, "member": 2490, "bar": 2491, "25euros": 2492, "viable": 2493, "savory": 2494, "10": 2495, "beats": 2496, "summer": 2497, "catered": 2498, "\u00a3,": 2499, "within": 2500, "better": 2501, "'": 2502, "visit": 2503, "nothing": 2504, "result": 2505, "Want": 2506, "fantastic": 2507, "Despite": 2508, "Fancy": 2509, "awarded": 2510, "working": 2511, "cast": 2512, "mot": 2513, "by": 2514, "ideally": 2515, "profits": 2516, "Thames": 2517, "accessible": 2518, "southpawn": 2519, "residing": 2520, "typical": 2521, "Specializing": 2522, "discriminating": 2523, "Tucson": 2524, "classics": 2525, "toilets": 2526, "less": 2527, "fruits": 2528, "gotten": 2529, "individual": 2530, "Wakey": 2531, "seem": 2532, "tow": 2533, "hit": 2534, "Compared": 2535, "district": 2536, "Do": 2537, "fondues": 2538, "negative": 2539, "attentive": 2540, "shop": 2541, "gourmet": 2542, "delight": 2543, "Parents": 2544, "matter": 2545, "The": 2546, "am": 2547, "plate": 2548, "goes": 2549, "deserts": 2550, "fair": 2551, "Locates": 2552, "Hire": 2553, "me": 2554, "barely": 2555, "overlooks": 2556, "Wildwood": 2557, "terrible": 2558, "watch": 2559, "Off": 2560, "afternoon": 2561, "anything": 2562, "finally": 2563, "friend": 2564, "cuisines": 2565, "busy": 2566, "lie": 2567, "grate": 2568, "server": 2569, "adjourning": 2570, "Who": 2571, "satisfaction": 2572, "Unfriendly": 2573, "ll": 2574, "keeping": 2575, "Watermans": 2576, "unfortunately": 2577, "1out": 2578, "theme": 2579, "attention": 2580, "promises": 2581, "accommodate": 2582, "favorites": 2583, "local": 2584, "includes": 2585, "favorable": 2586, "mid": 2587, "achieves": 2588, "easy": 2589, "Styled": 2590, "It": 2591, "brag": 2592, "add": 2593, "Next": 2594, "experience": 2595, "Try": 2596, "updated": 2597, "palate": 2598, "lunches": 2599, "hang": 2600, "ti": 2601, "centre": 2602, "excellently": 2603, "others": 2604, "By": 2605, "exotic": 2606, "UK": 2607, "Breakfast": 2608, "herbs": 2609, "feast": 2610, "youngster": 2611, "known": 2612, "middling": 2613, "pubs": 2614, "setup": 2615, "beverage": 2616, "recently": 2617, "farm": 2618, "person": 2619, "cooking": 2620, "ration": 2621, "proud": 2622, "eggs": 2623, "Treat": 2624, "Feel": 2625, "legendary": 2626, "spacious": 2627, "receiving": 2628, "speak": 2629, "type": 2630, "Come": 2631, "deter": 2632, "Priced": 2633, "into": 2634, "babysitter": 2635, "frenziedly": 2636, "being": 2637, "whole": 2638, "Rather": 2639, "Just": 2640, "Steve": 2641, "indicates": 2642, "make": 2643, "bes": 2644, "Sorrento": 2645, "disappointing": 2646, "moderate": 2647, "Have": 2648, "celebrate": 2649, "Passing": 2650, "north": 2651, "today": 2652, "ready": 2653, "With": 2654, "bucks": 2655, "Poorly": 2656, "thought": 2657, "respite": 2658, "specialty": 2659, "lover": 2660, "late": 2661, "albeit": 2662, "aren": 2663, "Rich": 2664, "sales": 2665, "occasion": 2666, "Tapas": 2667, "l20": 2668, "suffered": 2669, "charts": 2670, "exciting": 2671, "satisfactory": 2672, "NON": 2673, "surveillance": 2674, "Number": 2675, "filled": 2676, "Beefeaters": 2677, "luxurious": 2678, "Two": 2679, "will": 2680, "effective": 2681, "odious": 2682, "locale": 2683, "normal": 2684, "economical": 2685, "margin": 2686, "eat": 2687, "such": 2688, "Welcoming": 2689, "thing": 2690, "comparable": 2691, "]": 2692, "adults": 2693, "Punter": 2694, "Beautiful": 2695, "etc": 2696, "past": 2697, "why": 2698, "nearer": 2699, "Lower": 2700, "locater": 2701, "Yes": 2702, "fit": 2703, "afford": 2704, "classified": 2705, "inside": 2706, "amongst": 2707, "introducing": 2708, "Recent": 2709, "unmissable": 2710, "Start": 2711, "got": 2712, "foe": 2713, "ponds": 2714, "when": 2715, "health": 2716, "tailors": 2717, "members": 2718, "featuring": 2719, "spend": 2720, "these": 2721, "child": 2722, "gather": 2723, "airing": 2724, "+.": 2725, "eaten": 2726, "College": 2727, "adjacent": 2728, "Fittingly": 2729, "reasonable": 2730, "top": 2731, "noises": 2732, "course": 2733, "bang": 2734, "critics": 2735, "particular": 2736, "regarded": 2737, "claiming": 2738, "Family": 2739, "Cheat": 2740, "hotels": 2741, "manner": 2742, "ear": 2743, "Selling": 2744, "craving": 2745, "grown": 2746, "Bad": 2747, "For": 2748, "accommodations": 2749, "30pounds": 2750, "vino": 2751, "none": 2752, "providing": 2753, "plan": 2754, "gives": 2755, "diamond": 2756, "entertaining": 2757, "centrally": 2758, "priority": 2759, "singletons": 2760, "prams": 2761, "isn": 2762, "Fairly": 2763, "Tasty": 2764, "corner": 2765, "idea": 2766, "Costing": 2767, "greater": 2768, "24": 2769, "maybe": 2770, "Near": 2771, "Raja": 2772, "suitably": 2773, "wonderful": 2774, "35": 2775, "grand": 2776, "marketplace": 2777, "it": 2778, "Don": 2779, "laid": 2780, "Previous": 2781, "menu": 2782, "Plaza": 2783, "town": 2784, "sheep": 2785, "Japaneses": 2786, "worry": 2787, "-": 2788, "lose": 2789, "received": 2790, "rejects": 2791, "fast": 2792, "Holiday": 2793, "pleasing": 2794, "deliveries": 2795, "rub": 2796, "did": 2797, ",": 2798, "lies": 2799, "Did": 2800, "neighboring": 2801, "fyne": 2802, "incredibly": 2803, "Rated": 2804, "lees": 2805, "hankering": 2806, "unsatisfactory": 2807, "offering": 2808, "Paying": 2809, "expected": 2810, "Looking": 2811, "sered": 2812, "names": 2813, "prompt": 2814, "river": 2815, "Scored": 2816, "varies": 2817, "starring": 2818, "As": 2819, "suggests": 2820, "Expect": 2821, "cut": 2822, "alcoholic": 2823, "Top": 2824, "Sip": 2825, "dines": 2826, "climbing": 2827, "bit": 2828, "At": 2829, "wanted": 2830, "ow": 2831, "draw": 2832, "din": 2833, "each": 2834, "school": 2835, "serves": 2836, "a1out": 2837, "considers": 2838, "Where": 2839, "Pasta": 2840, "resort": 2841, "parties": 2842, "rates": 2843, "touring": 2844, "call": 2845, "raring": 2846, "goods": 2847, "cation": 2848, "popular": 2849, "Leave": 2850, "ruin": 2851, "though": 2852, "try": 2853, "unfamiliar": 2854, "Stunning": 2855, "longer": 2856, "Would": 2857, "Ia": 2858, "run": 2859, "instance": 2860, "nested": 2861, "upmarket": 2862, "shitty": 2863, "entrees": 2864, "toward": 2865, "cheaper": 2866, "One": 2867, "Grab": 2868, "lads": 2869, "Almost": 2870, "spaghetti": 2871, "Spectrum": 2872, "earns": 2873, "brasserie": 2874, "year": 2875, "Quality": 2876, "theres": 2877, "bring": 2878, "place": 2879, "Giraffes": 2880, "places": 2881, "dumpling": 2882, "sell": 2883, "wouldn": 2884, "40": 2885, "crumpets": 2886, "raving": 2887, "greatest": 2888, "appetizer": 2889, "history": 2890, "ladder": 2891, "Sits": 2892, "hilariously": 2893, "steadily": 2894, "quid": 2895, "family": 2896, "tastes": 2897, "fatty": 2898, "badly": 2899, "meetings": 2900, "fool": 2901, "approval": 2902, "beginning": 2903, "ranges": 2904, "unwelcoming": 2905, "more": 2906, "public": 2907, "polite": 2908, "friends": 2909, "hear": 2910, "competitor": 2911, "boasts": 2912, "Steak": 2913, "seek": 2914, "Whilst": 2915, "charges": 2916, "stuff": 2917, "Ranging": 2918, "rater": 2919, "fresh": 2920, "foods": 2921, "entries": 2922, "euro": 2923, "Consumer": 2924, "amusing": 2925, "ordered": 2926, "Bart": 2927, "garnered": 2928, "Blue": 2929, "couldn": 2930, "Cheap": 2931, "trendy": 2932, "Right": 2933, "L30": 2934, "lets": 2935, "Let": 2936, "Bells": 2937, "cooked": 2938, "traditional": 2939, "target": 2940, "Many": 2941, "early": 2942, "bracket": 2943, "inappropriate": 2944, "delectables": 2945, "currently": 2946, "yourself": 2947, "<unk>": 2948}